LICENSE
MANIFEST.in
README.md
setup.cfg
setup.py
pycicle/__init__.py
pycicle/cmd_gui.py
pycicle/cmd_parser.py
pycicle/custom_types.py
pycicle/exceptions.py
pycicle/help_funcs.py
pycicle.egg-info/PKG-INFO
pycicle.egg-info/SOURCES.txt
pycicle.egg-info/dependency_links.txt
pycicle.egg-info/top_level.txt
pycicle/examples/callable.py
pycicle/examples/sayit.py
pycicle/examples/ship.py
pycicle/examples/some_app.py
pycicle/examples/start_server.py
pycicle/images/icon.png
pycicle/images/sub_window.png
pycicle/images/talk.PNG
pycicle/images/window.PNG
pycicle/tools/__init__.py
pycicle/tools/document.py
pycicle/tools/parsers.py
pycicle/tools/tktooltip.py
pycicle/tools/utils.py
pycicle/unittests/test_pycicle.py
pycicle/unittests/test_runnables.py
pycicle/unittests/test_tools.py
pycicle/unittests/testing_tools.py