Metadata-Version: 2.1
Name: pycicle
Version: 0.1.5
Summary: command line parsers for the 21st century
Home-page: https://github.com/gemerden/pycicle
Author: Lars van Gemerden
Author-email: gemerden@gmail.com
License: MIT License
Keywords: command line parser argparser optparser GUI prompt
Platform: UNKNOWN
Classifier: Development Status :: 3 - Alpha
Classifier: Intended Audience :: Developers
Classifier: Topic :: Software Development
Classifier: License :: OSI Approved :: MIT License
Classifier: Programming Language :: Python :: 3.7
Classifier: Programming Language :: Python :: 3.8
Classifier: Programming Language :: Python :: 3.9
Requires-Python: >=3.7
License-File: LICENSE
